pydrifter/__init__.py
pydrifter/auxiliaries/__init__.py
pydrifter/auxiliaries/custom_warnings.py
pydrifter/base_classes/base_statistics.py
pydrifter/calculations/__init__.py
pydrifter/calculations/stat.py
pydrifter/calculations/stat_tests/__init__.py
pydrifter/calculations/stat_tests/kl_divergence.py
pydrifter/calculations/stat_tests/kstest.py
pydrifter/calculations/stat_tests/mannwhitney.py
pydrifter/calculations/stat_tests/psi.py
pydrifter/calculations/stat_tests/ttest.py
pydrifter/calculations/stat_tests/wasserstein.py
pydrifter/config/__init__.py
pydrifter/config/table_data.py
pydrifter/connections/__init__.py
pydrifter/connections/dataloader.py
pydrifter/connections/oracle.py
pydrifter/connections/postgres.py
pydrifter/connections/s3.py
pydrifter/logger.py
pydrifter/module/__init__.py
pydrifter/module/income.py
pydrifter-0.1.8.dist-info/LICENSE
pydrifter-0.1.8.dist-info/METADATA
pydrifter-0.1.8.dist-info/WHEEL
pydrifter-0.1.8.dist-info/RECORD
