Metadata-Version: 2.1
Name: pydrifter
Version: 0.1.8
Summary: Data drift checking for ML projects
Author: aesedeu
Author-email: aesedeu@gmail.com
Requires-Python: >=3.11,<4.0
Classifier: Programming Language :: Python :: 3
Classifier: Programming Language :: Python :: 3.11
Classifier: Programming Language :: Python :: 3.12
Requires-Dist: boto3 (>=1.38.5,<2.0.0)
Requires-Dist: fastparquet (>=2024.11.0,<2025.0.0)
Requires-Dist: ipywidgets (>=8.1.6,<9.0.0)
Requires-Dist: numpy (>=2.2.4,<3.0.0)
Requires-Dist: omegaconf (>=2.3.0,<3.0.0)
Requires-Dist: openpyxl (>=3.1.5,<4.0.0)
Requires-Dist: pandas (>=2.2.3,<3.0.0)
Requires-Dist: pendulum (>=3.0.0,<4.0.0)
Requires-Dist: psycopg2-binary (>=2.9.10,<3.0.0)
Requires-Dist: pyarrow (>=20.0.0,<21.0.0)
Requires-Dist: scikit-learn (>=1.6.1,<2.0.0)
Requires-Dist: scipy (>=1.15.2,<2.0.0)
Requires-Dist: seaborn (>=0.13.2,<0.14.0)
Requires-Dist: sqlalchemy (>=2.0.40,<3.0.0)
Requires-Dist: tabulate (>=0.9.0,<0.10.0)
Requires-Dist: termcolor (>=3.0.1,<4.0.0)
Requires-Dist: tqdm (>=4.67.1,<5.0.0)
